pylogg/__init__.py
pylogg/jsonfs.py
pylogg/postgres.py
pylogg/settings.py
pylogg-0.4.1.dist-info/LICENSE
pylogg-0.4.1.dist-info/METADATA
pylogg-0.4.1.dist-info/WHEEL
pylogg-0.4.1.dist-info/top_level.txt
pylogg-0.4.1.dist-info/RECORD
