Metadata-Version: 2.1
Name: pylogg
Version: 0.4.1
Summary: Logging and YAML-based configuration modules in Python.
Author-email: Akhlak Mahmood <akhlakm@gatech.edu>
Project-URL: Homepage, https://github.com/akhlakm/python-logg
Project-URL: Bug Tracker, https://github.com/akhlakm/python-logg/issues
Keywords: logging,development
Classifier: Operating System :: OS Independent
Classifier: Programming Language :: Python :: 3
Classifier: License :: OSI Approved :: MIT License
Requires-Python: >=3.10
License-File: LICENSE
Requires-Dist: pyyaml
Provides-Extra: dev
Requires-Dist: pytest ; extra == 'dev'
Requires-Dist: pre-commit ; extra == 'dev'
Provides-Extra: postgres
Requires-Dist: pandas ; extra == 'postgres'
Requires-Dist: sshtunnel ; extra == 'postgres'
Requires-Dist: psycopg[binary] ; extra == 'postgres'
